{
  "info": {
    "name": "Ticket Booking System API",
    "_postman_id": "c5b9b8e8-0000-4000-8000-000000000001",
    "description": "Postman collection for testing Vintage Ticket Hub - Event Booking System API",
    "schema": "https://schema.getpostman.com/json/collection/v2.1.0/collection.json"
  },
  "item": [
    {
      "name": "Events",
      "item": [
        {
          "name": "Get All Events",
          "request": {
            "method": "GET",
            "header": [],
            "url": {
              "raw": "{{baseUrl}}/api/events",
              "host": [
                "{{baseUrl}}"
              ],
              "path": [
                "api",
                "events"
              ]
            },
            "description": "Retrieve all available events"
          },
          "response": []
        },
        {
          "name": "Get Events by Category",
          "request": {
            "method": "GET",
            "header": [],
            "url": {
              "raw": "{{baseUrl}}/api/events?category=Concert",
              "host": [
                "{{baseUrl}}"
              ],
              "path": [
                "api",
                "events"
              ],
              "query": [
                {
                  "key": "category",
                  "value": "Concert"
                }
              ]
            },
            "description": "Filter events by category (Concert, Theater, Sports, etc.)"
          },
          "response": []
        },
        {
          "name": "Get Events by Location",
          "request": {
            "method": "GET",
            "header": [],
            "url": {
              "raw": "{{baseUrl}}/api/events?location=Manila",
              "host": [
                "{{baseUrl}}"
              ],
              "path": [
                "api",
                "events"
              ],
              "query": [
                {
                  "key": "location",
                  "value": "Manila"
                }
              ]
            },
            "description": "Filter events by location"
          },
          "response": []
        },
        {
          "name": "Search Events",
          "request": {
            "method": "GET",
            "header": [],
            "url": {
              "raw": "{{baseUrl}}/api/events?q=jazz",
              "host": [
                "{{baseUrl}}"
              ],
              "path": [
                "api",
                "events"
              ],
              "query": [
                {
                  "key": "q",
                  "value": "jazz"
                }
              ]
            },
            "description": "Search events by keyword"
          },
          "response": []
        },
        {
          "name": "Get Event by ID",
          "request": {
            "method": "GET",
            "header": [],
            "url": {
              "raw": "{{baseUrl}}/api/events/1",
              "host": [
                "{{baseUrl}}"
              ],
              "path": [
                "api",
                "events",
                "1"
              ]
            },
            "description": "Retrieve a specific event by ID"
          },
          "response": []
        },
        {
          "name": "Create Event",
          "request": {
            "method": "POST",
            "header": [
              {
                "key": "Content-Type",
                "value": "application/json"
              }
            ],
            "body": {
              "mode": "raw",
              "raw": "{\n  \"title\": \"Vintage Jazz Night 2025\",\n  \"description\": \"An evening of classic jazz music from the 1940s-1960s featuring live band performances at an intimate vintage-themed venue.\",\n  \"category\": \"Concert\",\n  \"venue\": \"Manila Palace Theater\",\n  \"location\": \"Manila, Philippines\",\n  \"eventDate\": \"2025-12-15T19:00:00\",\n  \"price\": 2500.00,\n  \"availableSeats\": 150,\n  \"imageUrl\": \"https://images.unsplash.com/photo-1493225457124-a3eb161ffa5f?w=500\"\n}",
              "options": {
                "raw": {
                  "language": "json"
                }
              }
            },
            "url": {
              "raw": "{{baseUrl}}/api/events",
              "host": [
                "{{baseUrl}}"
              ],
              "path": [
                "api",
                "events"
              ]
            },
            "description": "Create a new event for ticket booking"
          },
          "response": []
        }
      ]
    },
    {
      "name": "Customers",
      "item": [
        {
          "name": "Get All Customers",
          "request": {
            "method": "GET",
            "header": [],
            "url": {
              "raw": "{{baseUrl}}/api/customers",
              "host": [
                "{{baseUrl}}"
              ],
              "path": [
                "api",
                "customers"
              ]
            },
            "description": "Retrieve all registered customers"
          },
          "response": []
        },
        {
          "name": "Get Customer by ID",
          "request": {
            "method": "GET",
            "header": [],
            "url": {
              "raw": "{{baseUrl}}/api/customers/1",
              "host": [
                "{{baseUrl}}"
              ],
              "path": [
                "api",
                "customers",
                "1"
              ]
            },
            "description": "Retrieve a specific customer by ID"
          },
          "response": []
        },
        {
          "name": "Create Customer",
          "request": {
            "method": "POST",
            "header": [
              {
                "key": "Content-Type",
                "value": "application/json"
              }
            ],
            "body": {
              "mode": "raw",
              "raw": "{\n  \"fullName\": \"Maria Santos\",\n  \"email\": \"maria.santos@example.com\",\n  \"phone\": \"+639171234567\"\n}",
              "options": {
                "raw": {
                  "language": "json"
                }
              }
            },
            "url": {
              "raw": "{{baseUrl}}/api/customers",
              "host": [
                "{{baseUrl}}"
              ],
              "path": [
                "api",
                "customers"
              ]
            },
            "description": "Register a new customer"
          },
          "response": []
        },
        {
          "name": "Create Customer 2",
          "request": {
            "method": "POST",
            "header": [
              {
                "key": "Content-Type",
                "value": "application/json"
              }
            ],
            "body": {
              "mode": "raw",
              "raw": "{\n  \"fullName\": \"Juan Dela Cruz\",\n  \"email\": \"juan.delacruz@example.com\",\n  \"phone\": \"+639175554433\"\n}",
              "options": {
                "raw": {
                  "language": "json"
                }
              }
            },
            "url": {
              "raw": "{{baseUrl}}/api/customers",
              "host": [
                "{{baseUrl}}"
              ],
              "path": [
                "api",
                "customers"
              ]
            },
            "description": "Register another customer for testing"
          },
          "response": []
        }
      ]
    },
    {
      "name": "Bookings",
      "item": [
        {
          "name": "Get All Bookings",
          "request": {
            "method": "GET",
            "header": [],
            "url": {
              "raw": "{{baseUrl}}/api/bookings",
              "host": [
                "{{baseUrl}}"
              ],
              "path": [
                "api",
                "bookings"
              ]
            },
            "description": "Retrieve all bookings in the system"
          },
          "response": []
        },
        {
          "name": "Get Booking by ID",
          "request": {
            "method": "GET",
            "header": [],
            "url": {
              "raw": "{{baseUrl}}/api/bookings/1",
              "host": [
                "{{baseUrl}}"
              ],
              "path": [
                "api",
                "bookings",
                "1"
              ]
            },
            "description": "Retrieve a specific booking by ID"
          },
          "response": []
        },
        {
          "name": "Create Booking",
          "request": {
            "method": "POST",
            "header": [
              {
                "key": "Content-Type",
                "value": "application/json"
              }
            ],
            "body": {
              "mode": "raw",
              "raw": "{\n  \"eventId\": 1,\n  \"customerId\": 1,\n  \"numberOfTickets\": 2,\n  \"paymentMethod\": \"Credit Card\"\n}",
              "options": {
                "raw": {
                  "language": "json"
                }
              }
            },
            "url": {
              "raw": "{{baseUrl}}/api/bookings",
              "host": [
                "{{baseUrl}}"
              ],
              "path": [
                "api",
                "bookings"
              ]
            },
            "description": "Create a new booking for an event"
          },
          "response": []
        },
        {
          "name": "Create Booking 2",
          "request": {
            "method": "POST",
            "header": [
              {
                "key": "Content-Type",
                "value": "application/json"
              }
            ],
            "body": {
              "mode": "raw",
              "raw": "{\n  \"eventId\": 1,\n  \"customerId\": 2,\n  \"numberOfTickets\": 4,\n  \"paymentMethod\": \"Debit Card\"\n}",
              "options": {
                "raw": {
                  "language": "json"
                }
              }
            },
            "url": {
              "raw": "{{baseUrl}}/api/bookings",
              "host": [
                "{{baseUrl}}"
              ],
              "path": [
                "api",
                "bookings"
              ]
            },
            "description": "Create another booking for testing"
          },
          "response": []
        }
      ]
    }
  ],
  "variable": [
    {
      "key": "baseUrl",
      "value": "http://localhost:8081",
      "type": "string"
    }
  ]
}
